SoybeanNext/__init__.py
SoybeanNext/forward.py
SoybeanNext/main.py
SoybeanNext/reader.py
SoybeanNext/transform.py
SoyDNGP-0.0.3.dist-info/METADATA
SoyDNGP-0.0.3.dist-info/WHEEL
SoyDNGP-0.0.3.dist-info/top_level.txt
SoyDNGP-0.0.3.dist-info/RECORD
